[{"n": "CABA, SIN ESPECIFICAR", "id": "02_0", "v": 0.16848955671402774, "c": "yellow", "max": 4472, "date": "08/15/21"}, {"n": "CABA, COMUNA 01", "id": "02_001", "v": 0.15842972309849282, "c": "yellow", "max": 402}, {"n": "CABA, COMUNA 02", "id": "02_002", "v": 0.18256290228203625, "c": "yellow", "max": 293}, {"n": "CABA, COMUNA 03", "id": "02_003", "v": 0.16803811173668254, "c": "yellow", "max": 346}, {"n": "CABA, COMUNA 04", "id": "02_004", "v": 0.18320610687022898, "c": "yellow", "max": 450}, {"n": "CABA, COMUNA 05", "id": "02_005", "v": 0.18104738154613464, "c": "yellow", "max": 293}, {"n": "CABA, COMUNA 06", "id": "02_006", "v": 0.13819479857215708, "c": "yellow", "max": 263}, {"n": "CABA, COMUNA 07", "id": "02_007", "v": 0.12399414776883687, "c": "yellow", "max": 316}, {"n": "CABA, COMUNA 08", "id": "02_008", "v": 0.1724770642201835, "c": "yellow", "max": 357}, {"n": "CABA, COMUNA 09", "id": "02_009", "v": 0.2157788267026298, "c": "yellow", "max": 280}, {"n": "CABA, COMUNA 10", "id": "02_010", "v": 0.12811791383219956, "c": "yellow", "max": 214}, {"n": "CABA, COMUNA 11", "id": "02_011", "v": 0.18488943488943488, "c": "yellow", "max": 264}, {"n": "CABA, COMUNA 12", "id": "02_012", "v": 0.191869918699187, "c": "yellow", "max": 325}, {"n": "CABA, COMUNA 13", "id": "02_013", "v": 0.21602231964926266, "c": "yellow", "max": 481}, {"n": "CABA, COMUNA 14", "id": "02_014", "v": 0.177734375, "c": "yellow", "max": 448}, {"n": "CABA, COMUNA 15", "id": "02_015", "v": 0.1921529175050302, "c": "yellow", "max": 362}, {"n": "Buenos Aires, SIN ESPECIFICAR", "id": "06_0", "v": 0.19512195121951217, "c": "yellow", "max": 63}, {"n": "Buenos Aires, COMUNA 01", "id": "06_001", "v": 0.0, "c": "green", "max": 0}, {"n": "Buenos Aires, COMUNA 05", "id": "06_005", "v": 0.0, "c": "green", "max": 0}, {"n": "Buenos Aires, Adolfo Alsina", "id": "06_007", "v": 0.07619047619047618, "c": "yellow", "max": 20}, {"n": "Buenos Aires, Adolfo Gonzales Chaves", "id": "06_014", "v": 0.018604651162790697, "c": "green", "max": 5}, {"n": "Buenos Aires, Alberti", "id": "06_021", "v": 0.006191950464396286, "c": "green", "max": 3}, {"n": "Buenos Aires, Almirante Brown", "id": "06_028", "v": 0.20026146898027097, "c": "yellow", "max": 1548}, {"n": "Buenos Aires, Avellaneda", "id": "06_035", "v": 0.17965154503616043, "c": "yellow", "max": 1062}, {"n": "Buenos Aires, Ayacucho", "id": "06_042", "v": 0.09899569583931134, "c": "yellow", "max": 72}, {"n": "Buenos Aires, Azul", "id": "06_049", "v": 0.16466234967622573, "c": "yellow", "max": 173}, {"n": "Buenos Aires, Bah\u00eda Blanca", "id": "06_056", "v": 0.28186072116707955, "c": "yellow", "max": 1055}, {"n": "Buenos Aires, Balcarce", "id": "06_063", "v": 0.049744897959183666, "c": "yellow", "max": 62}, {"n": "Buenos Aires, Baradero", "id": "06_070", "v": 0.2622107969151671, "c": "yellow", "max": 82}, {"n": "Buenos Aires, Arrecifes", "id": "06_077", "v": 0.06782945736434108, "c": "yellow", "max": 42}, {"n": "Buenos Aires, Benito Ju\u00e1rez", "id": "06_084", "v": 0.05232558139534884, "c": "green", "max": 9}, {"n": "Buenos Aires, Berazategui", "id": "06_091", "v": 0.15993170176437108, "c": "yellow", "max": 774}, {"n": "Buenos Aires, Berisso", "id": "06_098", "v": 0.09189189189189188, "c": "yellow", "max": 170}, {"n": "Buenos Aires, Bol\u00edvar", "id": "06_105", "v": 0.07270560190703217, "c": "yellow", "max": 127}, {"n": "Buenos Aires, Bragado", "id": "06_112", "v": 0.09291628334866604, "c": "yellow", "max": 106}, {"n": "Buenos Aires, Brandsen", "id": "06_119", "v": 0.09523809523809523, "c": "yellow", "max": 52}, {"n": "Buenos Aires, Campana", "id": "06_126", "v": 0.1264367816091954, "c": "yellow", "max": 212}, {"n": "Buenos Aires, Ca\u00f1uelas", "id": "06_134", "v": 0.11281489594742608, "c": "yellow", "max": 91}, {"n": "Buenos Aires, Capit\u00e1n Sarmiento", "id": "06_140", "v": 0.09459459459459459, "c": "yellow", "max": 20}, {"n": "Buenos Aires, Carlos Casares", "id": "06_147", "v": 0.011560693641618497, "c": "green", "max": 7}, {"n": "Buenos Aires, Carlos Tejedor", "id": "06_154", "v": 0.16538461538461538, "c": "yellow", "max": 41}, {"n": "Buenos Aires, Carmen de Areco", "id": "06_161", "v": 0.10984848484848485, "c": "yellow", "max": 33}, {"n": "Buenos Aires, Castelli", "id": "06_168", "v": 0.023809523809523808, "c": "green", "max": 4}, {"n": "Buenos Aires, Col\u00f3n", "id": "06_175", "v": 0.05922551252847381, "c": "yellow", "max": 23}, {"n": "Buenos Aires, Coronel de Marina L. Rosales", "id": "06_182", "v": 0.11580882352941177, "c": "yellow", "max": 61}, {"n": "Buenos Aires, Coronel Dorrego", "id": "06_189", "v": 0.10139860139860139, "c": "yellow", "max": 38}, {"n": "Buenos Aires, Coronel Pringles", "id": "06_196", "v": 0.15719063545150502, "c": "yellow", "max": 56}, {"n": "Buenos Aires, Coronel Su\u00e1rez", "id": "06_203", "v": 0.2846511627906977, "c": "yellow", "max": 286}, {"n": "Buenos Aires, Chacabuco", "id": "06_210", "v": 0.0823327615780446, "c": "yellow", "max": 102}, {"n": "Buenos Aires, Chascom\u00fas", "id": "06_217", "v": 0.11790393013100435, "c": "yellow", "max": 81}, {"n": "Buenos Aires, Chivilcoy", "id": "06_224", "v": 0.05438931297709924, "c": "yellow", "max": 133}, {"n": "Buenos Aires, Daireaux", "id": "06_231", "v": 0.20481927710843373, "c": "yellow", "max": 97}, {"n": "Buenos Aires, Dolores", "id": "06_238", "v": 0.11311053984575836, "c": "yellow", "max": 62}, {"n": "Buenos Aires, Ensenada", "id": "06_245", "v": 0.06515580736543909, "c": "yellow", "max": 83}, {"n": "Buenos Aires, Escobar", "id": "06_252", "v": 0.15184815184815184, "c": "yellow", "max": 552}, {"n": "Buenos Aires, Esteban Echeverr\u00eda", "id": "06_260", "v": 0.18820450885668277, "c": "yellow", "max": 846}, {"n": "Buenos Aires, Exaltaci\u00f3n de la Cruz", "id": "06_266", "v": 0.09957627118644068, "c": "yellow", "max": 57}, {"n": "Buenos Aires, Ezeiza", "id": "06_270", "v": 0.14835787089467725, "c": "yellow", "max": 356}, {"n": "Buenos Aires, Florencio Varela", "id": "06_274", "v": 0.18018639972385228, "c": "yellow", "max": 967}, {"n": "Buenos Aires, Florentino Ameghino", "id": "06_277", "v": 0.11564625850340136, "c": "yellow", "max": 37}, {"n": "Buenos Aires, General Alvarado", "id": "06_280", "v": 0.09492635024549918, "c": "yellow", "max": 49}, {"n": "Buenos Aires, General Alvear", "id": "06_287", "v": 0.0078125, "c": "green", "max": 1}, {"n": "Buenos Aires, General Arenales", "id": "06_294", "v": 0.14516129032258066, "c": "yellow", "max": 45}, {"n": "Buenos Aires, General Belgrano", "id": "06_301", "v": 0.11340206185567009, "c": "yellow", "max": 28}, {"n": "Buenos Aires, General Guido", "id": "06_308", "v": 0.08695652173913045, "c": "green", "max": 2}, {"n": "Buenos Aires, General Juan Madariaga", "id": "06_315", "v": 0.096045197740113, "c": "yellow", "max": 33}, {"n": "Buenos Aires, General La Madrid", "id": "06_322", "v": 0.04744525547445256, "c": "green", "max": 12}, {"n": "Buenos Aires, General Las Heras", "id": "06_329", "v": 0.12158054711246201, "c": "yellow", "max": 42}, {"n": "Buenos Aires, General Lavalle", "id": "06_336", "v": 0.18749999999999997, "c": "green", "max": 10}, {"n": "Buenos Aires, General Paz", "id": "06_343", "v": 0.058823529411764705, "c": "green", "max": 14}, {"n": "Buenos Aires, General Pinto", "id": "06_351", "v": 0.0449438202247191, "c": "green", "max": 14}, {"n": "Buenos Aires, General Pueyrred\u00f3n", "id": "06_357", "v": 0.15540244969378827, "c": "yellow", "max": 1393}, {"n": "Buenos Aires, General Rodr\u00edguez", "id": "06_364", "v": 0.1411833626244874, "c": "yellow", "max": 201}, {"n": "Buenos Aires, General San Mart\u00edn", "id": "06_371", "v": 0.20150474321229966, "c": "yellow", "max": 1185}, {"n": "Buenos Aires, General Viamonte", "id": "06_385", "v": 0.17253521126760565, "c": "yellow", "max": 59}, {"n": "Buenos Aires, General Villegas", "id": "06_392", "v": 0.039403620873269436, "c": "yellow", "max": 34}, {"n": "Buenos Aires, Guamin\u00ed", "id": "06_399", "v": 0.03308823529411765, "c": "green", "max": 13}, {"n": "Buenos Aires, Hip\u00f3lito Yrigoyen", "id": "06_406", "v": 0.17277486910994763, "c": "yellow", "max": 24}, {"n": "Buenos Aires, Hurlingham", "id": "06_408", "v": 0.12740076824583868, "c": "yellow", "max": 379}, {"n": "Buenos Aires, Ituzaing\u00f3", "id": "06_410", "v": 0.13316672616922526, "c": "yellow", "max": 370}, {"n": "Buenos Aires, Jos\u00e9 C. Paz", "id": "06_412", "v": 0.11673242051520075, "c": "yellow", "max": 489}, {"n": "Buenos Aires, Jun\u00edn", "id": "06_413", "v": 0.11820925553319919, "c": "yellow", "max": 235}, {"n": "Buenos Aires, La Costa", "id": "06_420", "v": 0.11350974930362118, "c": "yellow", "max": 155}, {"n": "Buenos Aires, La Matanza", "id": "06_427", "v": 0.20770900619473712, "c": "yellow", "max": 3630}, {"n": "Buenos Aires, Lan\u00fas", "id": "06_434", "v": 0.17665735331470664, "c": "yellow", "max": 1240}, {"n": "Buenos Aires, La Plata", "id": "06_441", "v": 0.14615443600950848, "c": "yellow", "max": 1738}, {"n": "Buenos Aires, Laprida", "id": "06_448", "v": 0.36401673640167365, "c": "yellow", "max": 73}, {"n": "Buenos Aires, Las Flores", "id": "06_455", "v": 0.03149606299212599, "c": "green", "max": 14}, {"n": "Buenos Aires, Leandro N. Alem", "id": "06_462", "v": 0.08532934131736528, "c": "yellow", "max": 64}, {"n": "Buenos Aires, Lezama", "id": "06_466", "v": 0.2727272727272727, "c": "green", "max": 21}, {"n": "Buenos Aires, Lincoln", "id": "06_469", "v": 0.045000000000000005, "c": "yellow", "max": 82}, {"n": "Buenos Aires, Lober\u00eda", "id": "06_476", "v": 0.012048192771084338, "c": "green", "max": 9}, {"n": "Buenos Aires, Lobos", "id": "06_483", "v": 0.05555555555555555, "c": "yellow", "max": 50}, {"n": "Buenos Aires, Lomas de Zamora", "id": "06_490", "v": 0.2002647731375617, "c": "yellow", "max": 1603}, {"n": "Buenos Aires, Luj\u00e1n", "id": "06_497", "v": 0.15921931176168466, "c": "yellow", "max": 260}, {"n": "Buenos Aires, Magdalena", "id": "06_505", "v": 0.37860082304526743, "c": "yellow", "max": 66}, {"n": "Buenos Aires, Maip\u00fa", "id": "06_511", "v": 0.05084745762711865, "c": "green", "max": 13}, {"n": "Buenos Aires, Malvinas Argentinas", "id": "06_515", "v": 0.18123179359134414, "c": "yellow", "max": 843}, {"n": "Buenos Aires, Mar Chiquita", "id": "06_518", "v": 0.152317880794702, "c": "yellow", "max": 46}, {"n": "Buenos Aires, Marcos Paz", "id": "06_525", "v": 0.15424164524421594, "c": "yellow", "max": 101}, {"n": "Buenos Aires, Mercedes", "id": "06_532", "v": 0.06978319783197832, "c": "yellow", "max": 108}, {"n": "Buenos Aires, Merlo", "id": "06_539", "v": 0.20734237829209898, "c": "yellow", "max": 1152}, {"n": "Buenos Aires, Monte", "id": "06_547", "v": 0.023715415019762844, "c": "green", "max": 17}, {"n": "Buenos Aires, Monte Hermoso", "id": "06_553", "v": 0.2333333333333333, "c": "yellow", "max": 36}, {"n": "Buenos Aires, Moreno", "id": "06_560", "v": 0.14697802197802198, "c": "yellow", "max": 994}, {"n": "Buenos Aires, Mor\u00f3n", "id": "06_568", "v": 0.1566951566951567, "c": "yellow", "max": 746}, {"n": "Buenos Aires, Navarro", "id": "06_574", "v": 0.013011152416356878, "c": "green", "max": 9}, {"n": "Buenos Aires, Necochea", "id": "06_581", "v": 0.046275395033860044, "c": "yellow", "max": 98}, {"n": "Buenos Aires, 9 de Julio", "id": "06_588", "v": 0.1762820512820513, "c": "yellow", "max": 201}, {"n": "Buenos Aires, Olavarr\u00eda", "id": "06_595", "v": 0.1512401693889897, "c": "yellow", "max": 229}, {"n": "Buenos Aires, Patagones", "id": "06_602", "v": 0.11774744027303755, "c": "yellow", "max": 73}, {"n": "Buenos Aires, Pehuaj\u00f3", "id": "06_609", "v": 0.15521978021978022, "c": "yellow", "max": 95}, {"n": "Buenos Aires, Pellegrini", "id": "06_616", "v": 0.36363636363636365, "c": "yellow", "max": 38}, {"n": "Buenos Aires, Pergamino", "id": "06_623", "v": 0.058863328822733416, "c": "yellow", "max": 168}, {"n": "Buenos Aires, Pila", "id": "06_630", "v": 0.20634920634920637, "c": "green", "max": 9}, {"n": "Buenos Aires, Pilar", "id": "06_638", "v": 0.12281383598911776, "c": "yellow", "max": 892}, {"n": "Buenos Aires, Pinamar", "id": "06_644", "v": 0.22100656455142229, "c": "yellow", "max": 113}, {"n": "Buenos Aires, Presidente Per\u00f3n", "id": "06_648", "v": 0.1464968152866242, "c": "yellow", "max": 158}, {"n": "Buenos Aires, Pu\u00e1n", "id": "06_651", "v": 0.21107266435986158, "c": "yellow", "max": 50}, {"n": "Buenos Aires, Punta Indio", "id": "06_655", "v": 0.06701030927835053, "c": "green", "max": 12}, {"n": "Buenos Aires, Quilmes", "id": "06_658", "v": 0.1947584789311408, "c": "yellow", "max": 1826}, {"n": "Buenos Aires, Ramallo", "id": "06_665", "v": 0.07468354430379748, "c": "yellow", "max": 52}, {"n": "Buenos Aires, Rauch", "id": "06_672", "v": 0.11825192802056554, "c": "yellow", "max": 42}, {"n": "Buenos Aires, Rivadavia", "id": "06_679", "v": 0.023598820058997053, "c": "green", "max": 15}, {"n": "Buenos Aires, Rojas", "id": "06_686", "v": 0.099601593625498, "c": "yellow", "max": 34}, {"n": "Buenos Aires, Roque P\u00e9rez", "id": "06_693", "v": 0.029268292682926828, "c": "green", "max": 20}, {"n": "Buenos Aires, Saavedra", "id": "06_700", "v": 0.07759882869692533, "c": "yellow", "max": 51}, {"n": "Buenos Aires, Saladillo", "id": "06_707", "v": 0.07965860597439545, "c": "yellow", "max": 69}, {"n": "Buenos Aires, Salto", "id": "06_714", "v": 0.14128728414442698, "c": "yellow", "max": 77}, {"n": "Buenos Aires, Salliquel\u00f3", "id": "06_721", "v": 0.09770114942528736, "c": "green", "max": 14}, {"n": "Buenos Aires, San Andr\u00e9s de Giles", "id": "06_728", "v": 0.09195402298850573, "c": "yellow", "max": 53}, {"n": "Buenos Aires, San Antonio de Areco", "id": "06_735", "v": 0.20068027210884357, "c": "yellow", "max": 68}, {"n": "Buenos Aires, San Cayetano", "id": "06_742", "v": 0.0, "c": "green", "max": 2}, {"n": "Buenos Aires, San Fernando", "id": "06_749", "v": 0.14845516201959308, "c": "yellow", "max": 371}, {"n": "Buenos Aires, San Isidro", "id": "06_756", "v": 0.1899725812769291, "c": "yellow", "max": 864}, {"n": "Buenos Aires, San Miguel", "id": "06_760", "v": 0.26515151515151514, "c": "yellow", "max": 1192}, {"n": "Buenos Aires, San Nicol\u00e1s", "id": "06_763", "v": 0.18354430379746833, "c": "yellow", "max": 371}, {"n": "Buenos Aires, San Pedro", "id": "06_770", "v": 0.15841584158415842, "c": "yellow", "max": 193}, {"n": "Buenos Aires, San Vicente", "id": "06_778", "v": 0.10256410256410256, "c": "yellow", "max": 162}, {"n": "Buenos Aires, Suipacha", "id": "06_784", "v": 0.043478260869565216, "c": "green", "max": 7}, {"n": "Buenos Aires, Tandil", "id": "06_791", "v": 0.1596223021582734, "c": "yellow", "max": 334}, {"n": "Buenos Aires, Tapalqu\u00e9", "id": "06_798", "v": 0.08176100628930817, "c": "green", "max": 21}, {"n": "Buenos Aires, Tigre", "id": "06_805", "v": 0.17615563091201145, "c": "yellow", "max": 892}, {"n": "Buenos Aires, Tordillo", "id": "06_812", "v": 0.05714285714285715, "c": "green", "max": 1}, {"n": "Buenos Aires, Tornquist", "id": "06_819", "v": 0.3236245954692557, "c": "yellow", "max": 91}, {"n": "Buenos Aires, Trenque Lauquen", "id": "06_826", "v": 0.13858424725822532, "c": "yellow", "max": 166}, {"n": "Buenos Aires, Tres Arroyos", "id": "06_833", "v": 0.06568364611260055, "c": "yellow", "max": 106}, {"n": "Buenos Aires, Tres de Febrero", "id": "06_840", "v": 0.18133068520357498, "c": "yellow", "max": 853}, {"n": "Buenos Aires, Tres Lomas", "id": "06_847", "v": 0.3700787401574803, "c": "yellow", "max": 40}, {"n": "Buenos Aires, 25 de Mayo", "id": "06_854", "v": 0.20081967213114757, "c": "yellow", "max": 100}, {"n": "Buenos Aires, Vicente L\u00f3pez", "id": "06_861", "v": 0.14619164619164618, "c": "yellow", "max": 600}, {"n": "Buenos Aires, Villa Gesell", "id": "06_868", "v": 0.10029069767441862, "c": "yellow", "max": 81}, {"n": "Buenos Aires, Villarino", "id": "06_875", "v": 0.288135593220339, "c": "yellow", "max": 41}, {"n": "Buenos Aires, Z\u00e1rate", "id": "06_882", "v": 0.13752808988764045, "c": "yellow", "max": 300}, {"n": "Catamarca, SIN ESPECIFICAR", "id": "10_0", "v": 0.08771929824561403, "c": "green", "max": 6}, {"n": "Catamarca, Ambato", "id": "10_007", "v": 0.10869565217391305, "c": "green", "max": 21}, {"n": "Catamarca, Ancasti", "id": "10_014", "v": 0.23913043478260873, "c": "green", "max": 11}, {"n": "Catamarca, Andalgal\u00e1", "id": "10_021", "v": 0.14416058394160586, "c": "yellow", "max": 76}, {"n": "Catamarca, Antofagasta de la Sierra", "id": "10_028", "v": 0.0510204081632653, "c": "green", "max": 5}, {"n": "Catamarca, Bel\u00e9n", "id": "10_035", "v": 0.2152777777777778, "c": "yellow", "max": 46}, {"n": "Catamarca, Capay\u00e1n", "id": "10_042", "v": 0.13347022587268992, "c": "yellow", "max": 73}, {"n": "Catamarca, Capital", "id": "10_049", "v": 0.2068372393033756, "c": "yellow", "max": 912}, {"n": "Catamarca, El Alto", "id": "10_056", "v": 0.25490196078431376, "c": "green", "max": 9}, {"n": "Catamarca, Fray Mamerto Esqui\u00fa", "id": "10_063", "v": 0.166270783847981, "c": "yellow", "max": 70}, {"n": "Catamarca, La Paz", "id": "10_070", "v": 0.26203966005665724, "c": "yellow", "max": 180}, {"n": "Catamarca, Pacl\u00edn", "id": "10_077", "v": 0.1566265060240964, "c": "green", "max": 7}, {"n": "Catamarca, Pom\u00e1n", "id": "10_084", "v": 0.45493562231759654, "c": "orange", "max": 87}, {"n": "Catamarca, Santa Mar\u00eda", "id": "10_091", "v": 0.8999999999999999, "c": "red", "max": 199}, {"n": "Catamarca, Santa Rosa", "id": "10_098", "v": 0.2559241706161137, "c": "yellow", "max": 58}, {"n": "Catamarca, Tinogasta", "id": "10_105", "v": 0.04142011834319527, "c": "green", "max": 9}, {"n": "Catamarca, Valle Viejo", "id": "10_112", "v": 0.2995169082125604, "c": "yellow", "max": 234}, {"n": "C\u00f3rdoba, SIN ESPECIFICAR", "id": "14_0", "v": 0.23076923076923075, "c": "yellow", "max": 75}, {"n": "C\u00f3rdoba, Calamuchita", "id": "14_007", "v": 0.21226053639846743, "c": "yellow", "max": 260}, {"n": "C\u00f3rdoba, Capital", "id": "14_014", "v": 0.1598396622471004, "c": "yellow", "max": 6405}, {"n": "C\u00f3rdoba, Col\u00f3n", "id": "14_021", "v": 0.19146465379590652, "c": "yellow", "max": 1297}, {"n": "C\u00f3rdoba, Cruz del Eje", "id": "14_028", "v": 0.2580645161290323, "c": "yellow", "max": 381}, {"n": "C\u00f3rdoba, General Roca", "id": "14_035", "v": 0.1281094527363184, "c": "yellow", "max": 136}, {"n": "C\u00f3rdoba, General San Mart\u00edn", "id": "14_042", "v": 0.23273346303501946, "c": "yellow", "max": 1051}, {"n": "C\u00f3rdoba, Ischil\u00edn", "id": "14_049", "v": 0.14845173041894355, "c": "yellow", "max": 164}, {"n": "C\u00f3rdoba, Ju\u00e1rez Celman", "id": "14_056", "v": 0.23835319609967498, "c": "yellow", "max": 217}, {"n": "C\u00f3rdoba, Marcos Ju\u00e1rez", "id": "14_063", "v": 0.10611510791366907, "c": "yellow", "max": 347}, {"n": "C\u00f3rdoba, Minas", "id": "14_070", "v": 0.15789473684210525, "c": "yellow", "max": 19}, {"n": "C\u00f3rdoba, Pocho", "id": "14_077", "v": 0.1639344262295082, "c": "yellow", "max": 21}, {"n": "C\u00f3rdoba, Presidente Roque S\u00e1enz Pe\u00f1a", "id": "14_084", "v": 0.3256830601092896, "c": "yellow", "max": 239}, {"n": "C\u00f3rdoba, Punilla", "id": "14_091", "v": 0.20087019579405366, "c": "yellow", "max": 767}, {"n": "C\u00f3rdoba, R\u00edo Cuarto", "id": "14_098", "v": 0.23941334435034084, "c": "yellow", "max": 1169}, {"n": "C\u00f3rdoba, R\u00edo Primero", "id": "14_105", "v": 0.1912532637075718, "c": "yellow", "max": 268}, {"n": "C\u00f3rdoba, R\u00edo Seco", "id": "14_112", "v": 0.0881057268722467, "c": "yellow", "max": 57}, {"n": "C\u00f3rdoba, R\u00edo Segundo", "id": "14_119", "v": 0.17662721893491126, "c": "yellow", "max": 513}, {"n": "C\u00f3rdoba, San Alberto", "id": "14_126", "v": 0.2672998643147897, "c": "yellow", "max": 322}, {"n": "C\u00f3rdoba, San Javier", "id": "14_133", "v": 0.15476190476190477, "c": "yellow", "max": 247}, {"n": "C\u00f3rdoba, San Justo", "id": "14_140", "v": 0.06906614785992218, "c": "yellow", "max": 377}, {"n": "C\u00f3rdoba, Santa Mar\u00eda", "id": "14_147", "v": 0.17192746809939558, "c": "yellow", "max": 579}, {"n": "C\u00f3rdoba, Sobremonte", "id": "14_154", "v": 0.6145833333333334, "c": "orange", "max": 51}, {"n": "C\u00f3rdoba, Tercero Arriba", "id": "14_161", "v": 0.206286836935167, "c": "yellow", "max": 382}, {"n": "C\u00f3rdoba, Totoral", "id": "14_168", "v": 0.3547619047619048, "c": "yellow", "max": 108}, {"n": "C\u00f3rdoba, Tulumba", "id": "14_175", "v": 0.14460784313725492, "c": "yellow", "max": 57}, {"n": "C\u00f3rdoba, Uni\u00f3n", "id": "14_182", "v": 0.14241486068111456, "c": "yellow", "max": 435}, {"n": "Corrientes, SIN ESPECIFICAR", "id": "18_0", "v": 0.12, "c": "green", "max": 4}, {"n": "Corrientes, Bella Vista", "id": "18_007", "v": 0.17966903073286053, "c": "yellow", "max": 67}, {"n": "Corrientes, Ber\u00f3n de Astrada", "id": "18_014", "v": 0.06756756756756756, "c": "green", "max": 3}, {"n": "Corrientes, Capital", "id": "18_021", "v": 0.5062560153994226, "c": "orange", "max": 2701}, {"n": "Corrientes, Concepci\u00f3n", "id": "18_028", "v": 0.5799256505576208, "c": "orange", "max": 112}, {"n": "Corrientes, Curuz\u00fa Cuati\u00e1", "id": "18_035", "v": 0.23204419889502761, "c": "yellow", "max": 130}, {"n": "Corrientes, Empedrado", "id": "18_042", "v": 0.7232142857142857, "c": "orange", "max": 57}, {"n": "Corrientes, Esquina", "id": "18_049", "v": 0.36185383244206776, "c": "yellow", "max": 195}, {"n": "Corrientes, General Alvear", "id": "18_056", "v": 0.1739130434782609, "c": "green", "max": 5}, {"n": "Corrientes, General Paz", "id": "18_063", "v": 0.15625, "c": "yellow", "max": 40}, {"n": "Corrientes, Goya", "id": "18_070", "v": 0.4182415776499589, "c": "orange", "max": 419}, {"n": "Corrientes, Itat\u00ed", "id": "18_077", "v": 0.5106382978723404, "c": "orange", "max": 38}, {"n": "Corrientes, Ituzaing\u00f3", "id": "18_084", "v": 0.09157509157509157, "c": "yellow", "max": 55}, {"n": "Corrientes, Lavalle", "id": "18_091", "v": 0.3416988416988417, "c": "yellow", "max": 183}, {"n": "Corrientes, Mburucuy\u00e1", "id": "18_098", "v": 0.34220532319391633, "c": "yellow", "max": 91}, {"n": "Corrientes, Mercedes", "id": "18_105", "v": 0.29848693259972486, "c": "yellow", "max": 203}, {"n": "Corrientes, Monte Caseros", "id": "18_112", "v": 0.18865248226950357, "c": "yellow", "max": 118}, {"n": "Corrientes, Paso de los Libres", "id": "18_119", "v": 0.12582781456953643, "c": "yellow", "max": 84}, {"n": "Corrientes, Saladas", "id": "18_126", "v": 0.5904761904761905, "c": "orange", "max": 50}, {"n": "Corrientes, San Cosme", "id": "18_133", "v": 0.6744186046511628, "c": "orange", "max": 142}, {"n": "Corrientes, San Luis del Palmar", "id": "18_140", "v": 0.6487603305785123, "c": "orange", "max": 132}, {"n": "Corrientes, San Mart\u00edn", "id": "18_147", "v": 0.14166666666666666, "c": "yellow", "max": 34}, {"n": "Corrientes, San Miguel", "id": "18_154", "v": 0.4678899082568807, "c": "orange", "max": 34}, {"n": "Corrientes, San Roque", "id": "18_161", "v": 0.43915343915343924, "c": "orange", "max": 75}, {"n": "Corrientes, Santo Tom\u00e9", "id": "18_168", "v": 0.3524844720496894, "c": "yellow", "max": 185}, {"n": "Corrientes, Sauce", "id": "18_175", "v": 0.3, "c": "green", "max": 14}, {"n": "Chaco, SIN ESPECIFICAR", "id": "22_0", "v": 0.0, "c": "green", "max": 0}, {"n": "Chaco, Almirante Brown", "id": "22_007", "v": 0.37649880095923255, "c": "yellow", "max": 155}, {"n": "Chaco, Bermejo", "id": "22_014", "v": 0.24161073825503357, "c": "yellow", "max": 71}, {"n": "Chaco, Comandante Fern\u00e1ndez", "id": "22_021", "v": 0.5234042553191489, "c": "orange", "max": 470}, {"n": "Chaco, Chacabuco", "id": "22_028", "v": 0.14826498422712936, "c": "yellow", "max": 63}, {"n": "Chaco, 12 de Octubre", "id": "22_036", "v": 0.22994652406417113, "c": "yellow", "max": 92}, {"n": "Chaco, 2 de Abril", "id": "22_039", "v": 0.12831858407079644, "c": "yellow", "max": 40}, {"n": "Chaco, Fray Justo Santa Mar\u00eda de Oro", "id": "22_043", "v": 0.1388888888888889, "c": "yellow", "max": 30}, {"n": "Chaco, General Belgrano", "id": "22_049", "v": 0.044444444444444446, "c": "green", "max": 9}, {"n": "Chaco, General Donovan", "id": "22_056", "v": 0.3198757763975155, "c": "yellow", "max": 76}, {"n": "Chaco, General G\u00fcemes", "id": "22_063", "v": 0.38757396449704146, "c": "yellow", "max": 265}, {"n": "Chaco, Independencia", "id": "22_070", "v": 0.23348017621145375, "c": "yellow", "max": 47}, {"n": "Chaco, Libertad", "id": "22_077", "v": 0.12612612612612614, "c": "yellow", "max": 33}, {"n": "Chaco, Libertador General San Mart\u00edn", "id": "22_084", "v": 0.13580246913580246, "c": "yellow", "max": 95}, {"n": "Chaco, Maip\u00fa", "id": "22_091", "v": 0.4285714285714286, "c": "orange", "max": 168}, {"n": "Chaco, Mayor Luis J. Fontana", "id": "22_098", "v": 0.19011406844106463, "c": "yellow", "max": 164}, {"n": "Chaco, 9 de Julio", "id": "22_105", "v": 0.20608899297423888, "c": "yellow", "max": 86}, {"n": "Chaco, O'Higgins", "id": "22_112", "v": 0.31698113207547174, "c": "yellow", "max": 98}, {"n": "Chaco, Presidencia de la Plaza", "id": "22_119", "v": 0.16176470588235295, "c": "yellow", "max": 18}, {"n": "Chaco, 1\u00ba de Mayo", "id": "22_126", "v": 0.12578616352201258, "c": "yellow", "max": 37}, {"n": "Chaco, Quitilipi", "id": "22_133", "v": 0.344, "c": "yellow", "max": 106}, {"n": "Chaco, San Fernando", "id": "22_140", "v": 0.12593283582089554, "c": "yellow", "max": 1181}, {"n": "Chaco, San Lorenzo", "id": "22_147", "v": 0.3263157894736842, "c": "yellow", "max": 32}, {"n": "Chaco, Sargento Cabral", "id": "22_154", "v": 0.2956521739130435, "c": "yellow", "max": 36}, {"n": "Chaco, Tapenag\u00e1", "id": "22_161", "v": 0.0813953488372093, "c": "green", "max": 6}, {"n": "Chaco, 25 de Mayo", "id": "22_168", "v": 0.24115755627009644, "c": "yellow", "max": 71}, {"n": "Chubut, SIN ESPECIFICAR", "id": "26_0", "v": 0.05555555555555556, "c": "green", "max": 2}, {"n": "Chubut, Biedma", "id": "26_007", "v": 0.06015037593984962, "c": "yellow", "max": 78}, {"n": "Chubut, Cushamen", "id": "26_014", "v": 0.07112068965517242, "c": "yellow", "max": 34}, {"n": "Chubut, Escalante", "id": "26_021", "v": 0.22363002850807728, "c": "yellow", "max": 591}, {"n": "Chubut, Florentino Ameghino", "id": "26_028", "v": 0.325, "c": "green", "max": 12}, {"n": "Chubut, Futaleuf\u00fa", "id": "26_035", "v": 0.1782178217821782, "c": "yellow", "max": 172}, {"n": "Chubut, Gaiman", "id": "26_042", "v": 0.14379084967320263, "c": "green", "max": 24}, {"n": "Chubut, Gastre", "id": "26_049", "v": 0.0, "c": "green", "max": 0}, {"n": "Chubut, Langui\u00f1eo", "id": "26_056", "v": 0.15217391304347827, "c": "green", "max": 12}, {"n": "Chubut, M\u00e1rtires", "id": "26_063", "v": 0.0, "c": "green", "max": 0}, {"n": "Chubut, Paso de Indios", "id": "26_070", "v": 0.0, "c": "green", "max": 1}, {"n": "Chubut, Rawson", "id": "26_077", "v": 0.26703967446592064, "c": "yellow", "max": 430}, {"n": "Chubut, R\u00edo Senguer", "id": "26_084", "v": 0.009900990099009901, "c": "green", "max": 4}, {"n": "Chubut, Sarmiento", "id": "26_091", "v": 0.044186046511627906, "c": "yellow", "max": 15}, {"n": "Chubut, Tehuelches", "id": "26_098", "v": 0.09868421052631579, "c": "green", "max": 16}, {"n": "Chubut, Telsen", "id": "26_105", "v": 0.0, "c": "green", "max": 0}, {"n": "Entre R\u00edos, SIN ESPECIFICAR", "id": "30_0", "v": 0.0, "c": "green", "max": 0}, {"n": "Entre R\u00edos, Col\u00f3n", "id": "30_008", "v": 0.05722891566265059, "c": "yellow", "max": 85}, {"n": "Entre R\u00edos, Concordia", "id": "30_015", "v": 0.04134453781512605, "c": "yellow", "max": 133}, {"n": "Entre R\u00edos, Diamante", "id": "30_021", "v": 0.15283842794759825, "c": "yellow", "max": 103}, {"n": "Entre R\u00edos, Federaci\u00f3n", "id": "30_028", "v": 0.31460674157303375, "c": "yellow", "max": 158}, {"n": "Entre R\u00edos, Federal", "id": "30_035", "v": 0.07142857142857142, "c": "yellow", "max": 33}, {"n": "Entre R\u00edos, Feliciano", "id": "30_042", "v": 0.36746987951807225, "c": "yellow", "max": 60}, {"n": "Entre R\u00edos, Gualeguay", "id": "30_049", "v": 0.10414452709883104, "c": "yellow", "max": 95}, {"n": "Entre R\u00edos, Gualeguaych\u00fa", "id": "30_056", "v": 0.17520372526193248, "c": "yellow", "max": 313}, {"n": "Entre R\u00edos, Islas del Ibicuy", "id": "30_063", "v": 0.2557077625570776, "c": "yellow", "max": 58}, {"n": "Entre R\u00edos, La Paz", "id": "30_070", "v": 0.09325681492109038, "c": "yellow", "max": 69}, {"n": "Entre R\u00edos, Nogoy\u00e1", "id": "30_077", "v": 0.10229645093945722, "c": "yellow", "max": 47}, {"n": "Entre R\u00edos, Paran\u00e1", "id": "30_084", "v": 0.22091102194949255, "c": "yellow", "max": 853}, {"n": "Entre R\u00edos, San Salvador", "id": "30_088", "v": 0.028985507246376812, "c": "green", "max": 11}, {"n": "Entre R\u00edos, Tala", "id": "30_091", "v": 0.12442396313364057, "c": "yellow", "max": 64}, {"n": "Entre R\u00edos, Uruguay", "id": "30_098", "v": 0.1323308270676692, "c": "yellow", "max": 179}, {"n": "Entre R\u00edos, Victoria", "id": "30_105", "v": 0.24063116370808676, "c": "yellow", "max": 141}, {"n": "Entre R\u00edos, Villaguay", "id": "30_113", "v": 0.11808118081180811, "c": "yellow", "max": 63}, {"n": "Formosa, SIN ESPECIFICAR", "id": "34_0", "v": 0.0, "c": "green", "max": 0}, {"n": "Formosa, Bermejo", "id": "34_007", "v": 0.41025641025641024, "c": "orange", "max": 127}, {"n": "Formosa, Formosa", "id": "34_014", "v": 0.058078059399782306, "c": "yellow", "max": 687}, {"n": "Formosa, Laishi", "id": "34_021", "v": 0.28496503496503495, "c": "yellow", "max": 143}, {"n": "Formosa, Matacos", "id": "34_028", "v": 0.12806539509536785, "c": "yellow", "max": 32}, {"n": "Formosa, Pati\u00f1o", "id": "34_035", "v": 0.34528875379939206, "c": "yellow", "max": 443}, {"n": "Formosa, Pilag\u00e1s", "id": "34_042", "v": 0.08766233766233766, "c": "yellow", "max": 61}, {"n": "Formosa, Pilcomayo", "id": "34_049", "v": 0.0453887011105746, "c": "yellow", "max": 117}, {"n": "Formosa, Piran\u00e9", "id": "34_056", "v": 0.2920502092050209, "c": "yellow", "max": 321}, {"n": "Formosa, Ram\u00f3n Lista", "id": "34_063", "v": 0.4465753424657534, "c": "orange", "max": 153}, {"n": "Jujuy, SIN ESPECIFICAR", "id": "38_0", "v": 0.1, "c": "green", "max": 1}, {"n": "Jujuy, Cochinoca", "id": "38_007", "v": 0.04201680672268907, "c": "green", "max": 8}, {"n": "Jujuy, El Carmen", "id": "38_014", "v": 0.3621951219512195, "c": "yellow", "max": 280}, {"n": "Jujuy, Dr. Manuel Belgrano", "id": "38_021", "v": 0.4402470032691609, "c": "orange", "max": 1079}, {"n": "Jujuy, Humahuaca", "id": "38_028", "v": 0.13533834586466165, "c": "yellow", "max": 35}, {"n": "Jujuy, Ledesma", "id": "38_035", "v": 0.25611175785797435, "c": "yellow", "max": 209}, {"n": "Jujuy, Palpal\u00e1", "id": "38_042", "v": 0.2970873786407767, "c": "yellow", "max": 141}, {"n": "Jujuy, Rinconada", "id": "38_049", "v": 0.015037593984962405, "c": "green", "max": 1}, {"n": "Jujuy, San Antonio", "id": "38_056", "v": 0.10869565217391305, "c": "green", "max": 6}, {"n": "Jujuy, San Pedro", "id": "38_063", "v": 0.32963709677419356, "c": "yellow", "max": 265}, {"n": "Jujuy, Santa B\u00e1rbara", "id": "38_070", "v": 0.2474747474747475, "c": "yellow", "max": 52}, {"n": "Jujuy, Santa Catalina", "id": "38_077", "v": 0.0, "c": "green", "max": 0}, {"n": "Jujuy, Susques", "id": "38_084", "v": 0.03187250996015936, "c": "green", "max": 6}, {"n": "Jujuy, Tilcara", "id": "38_094", "v": 0.17834394904458598, "c": "yellow", "max": 28}, {"n": "Jujuy, Tumbaya", "id": "38_098", "v": 0.1846153846153846, "c": "green", "max": 6}, {"n": "Jujuy, Valle Grande", "id": "38_105", "v": 0.0, "c": "green", "max": 0}, {"n": "Jujuy, Yavi", "id": "38_112", "v": 0.024242424242424242, "c": "green", "max": 14}, {"n": "Jujuy, Campana", "id": "38_126", "v": 0.0, "c": "green", "max": 0}, {"n": "Jujuy, Coronel de Marina L. Rosales", "id": "38_182", "v": 0.0, "c": "green", "max": 0}, {"n": "Jujuy, General Guido", "id": "38_308", "v": 0.0, "c": "green", "max": 0}, {"n": "La Pampa, SIN ESPECIFICAR", "id": "42_0", "v": 0.0, "c": "green", "max": 0}, {"n": "La Pampa, Atreuc\u00f3", "id": "42_007", "v": 0.29791666666666666, "c": "yellow", "max": 165}, {"n": "La Pampa, Caleu Caleu", "id": "42_014", "v": 0.39344262295081966, "c": "yellow", "max": 18}, {"n": "La Pampa, Capital", "id": "42_021", "v": 0.11065032987747409, "c": "yellow", "max": 566}, {"n": "La Pampa, Catril\u00f3", "id": "42_028", "v": 0.08037825059101655, "c": "yellow", "max": 37}, {"n": "La Pampa, Conhelo", "id": "42_035", "v": 0.1001088139281828, "c": "yellow", "max": 69}, {"n": "La Pampa, Curac\u00f3", "id": "42_042", "v": 0.07843137254901962, "c": "green", "max": 4}, {"n": "La Pampa, Chalileo", "id": "42_049", "v": 0.06806282722513089, "c": "green", "max": 21}, {"n": "La Pampa, Chapaleuf\u00fa", "id": "42_056", "v": 0.17894736842105263, "c": "yellow", "max": 58}, {"n": "La Pampa, Chical Co", "id": "42_063", "v": 0.18749999999999997, "c": "green", "max": 6}, {"n": "La Pampa, Guatrach\u00e9", "id": "42_070", "v": 0.48322147651006714, "c": "orange", "max": 125}, {"n": "La Pampa, Hucal", "id": "42_077", "v": 0.5555555555555555, "c": "orange", "max": 114}, {"n": "La Pampa, Lihuel Calel", "id": "42_084", "v": 0.0, "c": "green", "max": 0}, {"n": "La Pampa, Limay Mahuida", "id": "42_091", "v": 0.04347826086956522, "c": "green", "max": 1}, {"n": "La Pampa, Loventu\u00e9", "id": "42_098", "v": 0.03986135181975736, "c": "yellow", "max": 33}, {"n": "La Pampa, Marac\u00f3", "id": "42_105", "v": 0.1301995265471762, "c": "yellow", "max": 364}, {"n": "La Pampa, Puel\u00e9n", "id": "42_112", "v": 0.05286343612334802, "c": "yellow", "max": 28}, {"n": "La Pampa, Quem\u00fa Quem\u00fa", "id": "42_119", "v": 0.08933002481389579, "c": "yellow", "max": 38}, {"n": "La Pampa, Rancul", "id": "42_126", "v": 0.2316715542521994, "c": "yellow", "max": 106}, {"n": "La Pampa, Realic\u00f3", "id": "42_133", "v": 0.11152882205513785, "c": "yellow", "max": 91}, {"n": "La Pampa, Toay", "id": "42_140", "v": 0.11714589989350373, "c": "yellow", "max": 115}, {"n": "La Pampa, Trenel", "id": "42_147", "v": 0.09935897435897437, "c": "yellow", "max": 27}, {"n": "La Pampa, Utrac\u00e1n", "id": "42_154", "v": 0.08386075949367088, "c": "yellow", "max": 56}, {"n": "La Rioja, SIN ESPECIFICAR", "id": "46_0", "v": 0.25, "c": "green", "max": 1}, {"n": "La Rioja, Arauco", "id": "46_007", "v": 0.10989010989010989, "c": "yellow", "max": 65}, {"n": "La Rioja, Capital", "id": "46_014", "v": 0.5234098939929328, "c": "orange", "max": 1034}, {"n": "La Rioja, Castro Barros", "id": "46_021", "v": 0.2072072072072072, "c": "green", "max": 22}, {"n": "La Rioja, Coronel Felipe Varela", "id": "46_028", "v": 0.055970149253731345, "c": "green", "max": 16}, {"n": "La Rioja, Chamical", "id": "46_035", "v": 0.21019108280254778, "c": "yellow", "max": 70}, {"n": "La Rioja, Chilecito", "id": "46_042", "v": 0.11874105865522175, "c": "yellow", "max": 82}, {"n": "La Rioja, Famatina", "id": "46_049", "v": 0.044642857142857144, "c": "green", "max": 15}, {"n": "La Rioja, General Angel V. Pe\u00f1aloza", "id": "46_056", "v": 0.27906976744186046, "c": "yellow", "max": 27}, {"n": "La Rioja, General Belgrano", "id": "46_063", "v": 0.20625, "c": "yellow", "max": 33}, {"n": "La Rioja, General Juan F. Quiroga", "id": "46_070", "v": 0.7272727272727273, "c": "orange", "max": 32}, {"n": "La Rioja, General Lamadrid", "id": "46_077", "v": 0.10526315789473684, "c": "green", "max": 4}, {"n": "La Rioja, General Ocampo", "id": "46_084", "v": 0.2384105960264901, "c": "yellow", "max": 32}, {"n": "La Rioja, General San Mart\u00edn", "id": "46_091", "v": 0.12658227848101264, "c": "green", "max": 11}, {"n": "La Rioja, Vinchina", "id": "46_098", "v": 0.07594936708860758, "c": "green", "max": 10}, {"n": "La Rioja, Independencia", "id": "46_105", "v": 0.23376623376623376, "c": "green", "max": 13}, {"n": "La Rioja, Rosario Vera Pe\u00f1aloza", "id": "46_112", "v": 0.28629032258064513, "c": "yellow", "max": 79}, {"n": "La Rioja, San Blas de los Sauces", "id": "46_119", "v": 0.4077669902912621, "c": "orange", "max": 39}, {"n": "La Rioja, Sanagasta", "id": "46_126", "v": 0.22641509433962265, "c": "green", "max": 10}, {"n": "Mendoza, SIN ESPECIFICAR", "id": "50_0", "v": 0.21538461538461537, "c": "green", "max": 10}, {"n": "Mendoza, Capital", "id": "50_007", "v": 0.17566765578635016, "c": "yellow", "max": 266}, {"n": "Mendoza, General Alvear", "id": "50_014", "v": 0.06139731827805222, "c": "yellow", "max": 84}, {"n": "Mendoza, Godoy Cruz", "id": "50_021", "v": 0.17460986925347954, "c": "yellow", "max": 421}, {"n": "Mendoza, Guaymall\u00e9n", "id": "50_028", "v": 0.20324922226062908, "c": "yellow", "max": 535}, {"n": "Mendoza, Jun\u00edn", "id": "50_035", "v": 0.14663461538461536, "c": "yellow", "max": 51}, {"n": "Mendoza, La Paz", "id": "50_042", "v": 0.07200000000000001, "c": "green", "max": 11}, {"n": "Mendoza, Las Heras", "id": "50_049", "v": 0.22938737908797788, "c": "yellow", "max": 471}, {"n": "Mendoza, Lavalle", "id": "50_056", "v": 0.24188790560471976, "c": "yellow", "max": 71}, {"n": "Mendoza, Luj\u00e1n de Cuyo", "id": "50_063", "v": 0.149393605292172, "c": "yellow", "max": 251}, {"n": "Mendoza, Maip\u00fa", "id": "50_070", "v": 0.22484352431391433, "c": "yellow", "max": 408}, {"n": "Mendoza, Malarg\u00fce", "id": "50_077", "v": 0.33969465648854963, "c": "yellow", "max": 97}, {"n": "Mendoza, Rivadavia", "id": "50_084", "v": 0.1174863387978142, "c": "yellow", "max": 72}, {"n": "Mendoza, San Carlos", "id": "50_091", "v": 0.10721649484536083, "c": "yellow", "max": 46}, {"n": "Mendoza, San Mart\u00edn", "id": "50_098", "v": 0.10610328638497653, "c": "yellow", "max": 104}, {"n": "Mendoza, San Rafael", "id": "50_105", "v": 0.18397720075997467, "c": "yellow", "max": 681}, {"n": "Mendoza, Santa Rosa", "id": "50_112", "v": 0.0339943342776204, "c": "green", "max": 10}, {"n": "Mendoza, Tunuy\u00e1n", "id": "50_119", "v": 0.11073825503355704, "c": "yellow", "max": 83}, {"n": "Mendoza, Tupungato", "id": "50_126", "v": 0.06990291262135923, "c": "yellow", "max": 41}, {"n": "Mendoza, General San Mart\u00edn", "id": "50_371", "v": 0.0, "c": "green", "max": 0}, {"n": "Misiones, SIN ESPECIFICAR", "id": "54_0", "v": 0.5, "c": "green", "max": 1}, {"n": "Misiones, Ap\u00f3stoles", "id": "54_007", "v": 0.40106951871657753, "c": "orange", "max": 61}, {"n": "Misiones, Caingu\u00e1s", "id": "54_014", "v": 0.2621359223300971, "c": "yellow", "max": 46}, {"n": "Misiones, Candelaria", "id": "54_021", "v": 0.5544554455445544, "c": "orange", "max": 46}, {"n": "Misiones, Capital", "id": "54_028", "v": 0.5602536997885835, "c": "orange", "max": 1040}, {"n": "Misiones, Concepci\u00f3n", "id": "54_035", "v": 0.6388888888888888, "c": "orange", "max": 15}, {"n": "Misiones, Eldorado", "id": "54_042", "v": 0.0962962962962963, "c": "yellow", "max": 53}, {"n": "Misiones, General Manuel Belgrano", "id": "54_049", "v": 0.07657657657657657, "c": "green", "max": 15}, {"n": "Misiones, Guaran\u00ed", "id": "54_056", "v": 0.11032863849765258, "c": "yellow", "max": 43}, {"n": "Misiones, Iguaz\u00fa", "id": "54_063", "v": 0.1705426356589147, "c": "yellow", "max": 73}, {"n": "Misiones, Leandro N. Alem", "id": "54_070", "v": 0.4145299145299145, "c": "orange", "max": 69}, {"n": "Misiones, Libertador Grl. San Mart\u00edn", "id": "54_077", "v": 0.4177777777777778, "c": "orange", "max": 72}, {"n": "Misiones, Montecarlo", "id": "54_084", "v": 0.20247933884297523, "c": "yellow", "max": 33}, {"n": "Misiones, Ober\u00e1", "id": "54_091", "v": 0.34444444444444444, "c": "yellow", "max": 143}, {"n": "Misiones, San Ignacio", "id": "54_098", "v": 0.20348837209302326, "c": "yellow", "max": 38}, {"n": "Misiones, San Javier", "id": "54_105", "v": 0.27999999999999997, "c": "green", "max": 7}, {"n": "Misiones, San Pedro", "id": "54_112", "v": 0.25225225225225223, "c": "yellow", "max": 19}, {"n": "Misiones, 25 de Mayo", "id": "54_119", "v": 0.0425531914893617, "c": "green", "max": 3}, {"n": "Neuqu\u00e9n, SIN ESPECIFICAR", "id": "58_0", "v": 0.0, "c": "green", "max": 1}, {"n": "Neuqu\u00e9n, Alumin\u00e9", "id": "58_007", "v": 0.20588235294117646, "c": "yellow", "max": 28}, {"n": "Neuqu\u00e9n, A\u00f1elo", "id": "58_014", "v": 0.20512820512820512, "c": "yellow", "max": 53}, {"n": "Neuqu\u00e9n, Cat\u00e1n Lil", "id": "58_021", "v": 0.0, "c": "green", "max": 0}, {"n": "Neuqu\u00e9n, Coll\u00f3n Cur\u00e1", "id": "58_028", "v": 0.0, "c": "green", "max": 1}, {"n": "Neuqu\u00e9n, Confluencia", "id": "58_035", "v": 0.16833313727796728, "c": "yellow", "max": 1329}, {"n": "Neuqu\u00e9n, Chos Malal", "id": "58_042", "v": 0.03967168262653899, "c": "yellow", "max": 22}, {"n": "Neuqu\u00e9n, Huiliches", "id": "58_049", "v": 0.07241379310344828, "c": "yellow", "max": 36}, {"n": "Neuqu\u00e9n, L\u00e1car", "id": "58_056", "v": 0.18028643639427125, "c": "yellow", "max": 193}, {"n": "Neuqu\u00e9n, Loncopu\u00e9", "id": "58_063", "v": 0.021621621621621623, "c": "green", "max": 5}, {"n": "Neuqu\u00e9n, Los Lagos", "id": "58_070", "v": 0.09090909090909091, "c": "yellow", "max": 34}, {"n": "Neuqu\u00e9n, Minas", "id": "58_077", "v": 0.0148975791433892, "c": "green", "max": 11}, {"n": "Neuqu\u00e9n, \u00d1orqu\u00edn", "id": "58_084", "v": 0.0, "c": "green", "max": 2}, {"n": "Neuqu\u00e9n, Pehuenches", "id": "58_091", "v": 0.04880478087649402, "c": "yellow", "max": 41}, {"n": "Neuqu\u00e9n, Pic\u00fan Leuf\u00fa", "id": "58_098", "v": 0.11458333333333334, "c": "green", "max": 9}, {"n": "Neuqu\u00e9n, Picunches", "id": "58_105", "v": 0.006060606060606061, "c": "green", "max": 4}, {"n": "Neuqu\u00e9n, Zapala", "id": "58_112", "v": 0.04057591623036649, "c": "yellow", "max": 22}, {"n": "R\u00edo Negro, SIN ESPECIFICAR", "id": "62_0", "v": 0.16666666666666669, "c": "green", "max": 1}, {"n": "R\u00edo Negro, Adolfo Alsina", "id": "62_007", "v": 0.04854368932038835, "c": "yellow", "max": 80}, {"n": "R\u00edo Negro, Avellaneda", "id": "62_014", "v": 0.18838028169014084, "c": "yellow", "max": 122}, {"n": "R\u00edo Negro, Bariloche", "id": "62_021", "v": 0.2461605967529618, "c": "yellow", "max": 486}, {"n": "R\u00edo Negro, Conesa", "id": "62_028", "v": 0.2543352601156069, "c": "yellow", "max": 39}, {"n": "R\u00edo Negro, El Cuy", "id": "62_035", "v": 0.08333333333333333, "c": "green", "max": 7}, {"n": "R\u00edo Negro, General Roca", "id": "62_042", "v": 0.2544692120944604, "c": "yellow", "max": 1156}, {"n": "R\u00edo Negro, 9 de Julio", "id": "62_049", "v": 0.0, "c": "green", "max": 1}, {"n": "R\u00edo Negro, \u00d1orquinc\u00f3", "id": "62_056", "v": 0.0, "c": "green", "max": 0}, {"n": "R\u00edo Negro, Pichi Mahuida", "id": "62_063", "v": 0.4253393665158371, "c": "orange", "max": 84}, {"n": "R\u00edo Negro, Pilcaniyeu", "id": "62_070", "v": 0.16546762589928055, "c": "green", "max": 19}, {"n": "R\u00edo Negro, San Antonio", "id": "62_077", "v": 0.15073529411764705, "c": "yellow", "max": 73}, {"n": "R\u00edo Negro, Valcheta", "id": "62_084", "v": 0.38317757009345793, "c": "yellow", "max": 27}, {"n": "R\u00edo Negro, 25 de Mayo", "id": "62_091", "v": 0.10526315789473684, "c": "yellow", "max": 39}, {"n": "Salta, SIN ESPECIFICAR", "id": "66_0", "v": 0.11111111111111112, "c": "green", "max": 3}, {"n": "Salta, Anta", "id": "66_007", "v": 0.18657453109575517, "c": "yellow", "max": 195}, {"n": "Salta, Cachi", "id": "66_014", "v": 0.10743801652892562, "c": "green", "max": 18}, {"n": "Salta, Cafayate", "id": "66_021", "v": 0.05837563451776649, "c": "green", "max": 24}, {"n": "Salta, Capital", "id": "66_028", "v": 0.2569287083841729, "c": "yellow", "max": 1368}, {"n": "Salta, Cerrillos", "id": "66_035", "v": 0.20759493670886073, "c": "yellow", "max": 79}, {"n": "Salta, Chicoana", "id": "66_042", "v": 0.07323232323232323, "c": "yellow", "max": 28}, {"n": "Salta, General G\u00fcemes", "id": "66_049", "v": 0.3333333333333333, "c": "yellow", "max": 121}, {"n": "Salta, Grl. Jos\u00e9 de San Mart\u00edn", "id": "66_056", "v": 0.5911799761620977, "c": "orange", "max": 417}, {"n": "Salta, Guachipas", "id": "66_063", "v": 0.05660377358490566, "c": "green", "max": 5}, {"n": "Salta, Iruya", "id": "66_070", "v": 0.044715447154471545, "c": "green", "max": 16}, {"n": "Salta, La Caldera", "id": "66_077", "v": 0.2216494845360825, "c": "yellow", "max": 44}, {"n": "Salta, La Candelaria", "id": "66_084", "v": 0.039473684210526314, "c": "green", "max": 14}, {"n": "Salta, La Poma", "id": "66_091", "v": 0.052631578947368425, "c": "green", "max": 6}, {"n": "Salta, La Vi\u00f1a", "id": "66_098", "v": 0.07228915662650602, "c": "green", "max": 12}, {"n": "Salta, Los Andes", "id": "66_105", "v": 0.04411764705882353, "c": "green", "max": 3}, {"n": "Salta, Met\u00e1n", "id": "66_112", "v": 0.05065666041275798, "c": "yellow", "max": 64}, {"n": "Salta, Molinos", "id": "66_119", "v": 0.08860759493670885, "c": "green", "max": 15}, {"n": "Salta, Or\u00e1n", "id": "66_126", "v": 0.2608187134502924, "c": "yellow", "max": 210}, {"n": "Salta, Rivadavia", "id": "66_133", "v": 0.3415384615384615, "c": "yellow", "max": 112}, {"n": "Salta, Rosario de la Frontera", "id": "66_140", "v": 0.03465346534653465, "c": "yellow", "max": 38}, {"n": "Salta, Rosario de Lerma", "id": "66_147", "v": 0.18181818181818182, "c": "yellow", "max": 85}, {"n": "Salta, San Carlos", "id": "66_154", "v": 0.075, "c": "green", "max": 15}, {"n": "Salta, Santa Victoria", "id": "66_161", "v": 0.14545454545454545, "c": "green", "max": 32}, {"n": "San Juan, SIN ESPECIFICAR", "id": "70_0", "v": 0.012738853503184714, "c": "green", "max": 4}, {"n": "San Juan, Albard\u00f3n", "id": "70_007", "v": 0.1729957805907173, "c": "yellow", "max": 75}, {"n": "San Juan, Angaco", "id": "70_014", "v": 0.34831460674157305, "c": "yellow", "max": 32}, {"n": "San Juan, Calingasta", "id": "70_021", "v": 0.2956521739130435, "c": "yellow", "max": 19}, {"n": "San Juan, Capital", "id": "70_028", "v": 0.25049407114624506, "c": "yellow", "max": 451}, {"n": "San Juan, Caucete", "id": "70_035", "v": 0.13179916317991633, "c": "yellow", "max": 63}, {"n": "San Juan, Chimbas", "id": "70_042", "v": 0.18277571251548946, "c": "yellow", "max": 282}, {"n": "San Juan, Iglesia", "id": "70_049", "v": 0.08620689655172414, "c": "green", "max": 13}, {"n": "San Juan, J\u00e1chal", "id": "70_056", "v": 0.21019108280254778, "c": "yellow", "max": 56}, {"n": "San Juan, 9 de Julio", "id": "70_063", "v": 0.33870967741935487, "c": "yellow", "max": 36}, {"n": "San Juan, Pocito", "id": "70_070", "v": 0.18812877263581487, "c": "yellow", "max": 179}, {"n": "San Juan, Rawson", "id": "70_077", "v": 0.19354838709677422, "c": "yellow", "max": 387}, {"n": "San Juan, Rivadavia", "id": "70_084", "v": 0.21535580524344572, "c": "yellow", "max": 343}, {"n": "San Juan, San Mart\u00edn", "id": "70_091", "v": 0.0893371757925072, "c": "yellow", "max": 21}, {"n": "San Juan, Santa Luc\u00eda", "id": "70_098", "v": 0.21832579185520362, "c": "yellow", "max": 186}, {"n": "San Juan, Sarmiento", "id": "70_105", "v": 0.109375, "c": "yellow", "max": 27}, {"n": "San Juan, Ull\u00fam", "id": "70_112", "v": 0.2558139534883721, "c": "green", "max": 20}, {"n": "San Juan, Valle F\u00e9rtil", "id": "70_119", "v": 0.2878048780487805, "c": "yellow", "max": 44}, {"n": "San Juan, 25 de Mayo", "id": "70_126", "v": 0.06666666666666667, "c": "yellow", "max": 19}, {"n": "San Juan, Zonda", "id": "70_133", "v": 0.15625, "c": "green", "max": 10}, {"n": "San Luis, SIN ESPECIFICAR", "id": "74_0", "v": 0.0, "c": "green", "max": 1}, {"n": "San Luis, Ayacucho", "id": "74_007", "v": 0.06732348111658457, "c": "yellow", "max": 56}, {"n": "San Luis, Belgrano", "id": "74_014", "v": 0.023529411764705882, "c": "green", "max": 11}, {"n": "San Luis, Coronel Pringles", "id": "74_021", "v": 0.15281501340482576, "c": "yellow", "max": 58}, {"n": "San Luis, Chacabuco", "id": "74_028", "v": 0.08365758754863813, "c": "yellow", "max": 35}, {"n": "San Luis, General Pedernera", "id": "74_035", "v": 0.1375036884036589, "c": "yellow", "max": 452}, {"n": "San Luis, Gobernador Dupuy", "id": "74_042", "v": 0.07360406091370558, "c": "yellow", "max": 23}, {"n": "San Luis, Jun\u00edn", "id": "74_049", "v": 0.31669044222539233, "c": "yellow", "max": 209}, {"n": "San Luis, La Capital", "id": "74_056", "v": 0.14836520666255398, "c": "yellow", "max": 893}, {"n": "San Luis, Libertador General San Mart\u00edn", "id": "74_063", "v": 0.03007518796992481, "c": "green", "max": 6}, {"n": "Santa Cruz, SIN ESPECIFICAR", "id": "78_0", "v": 0.05, "c": "green", "max": 1}, {"n": "Santa Cruz, Corpen Aike", "id": "78_007", "v": 0.03909465020576131, "c": "yellow", "max": 16}, {"n": "Santa Cruz, Deseado", "id": "78_014", "v": 0.09028960817717206, "c": "yellow", "max": 293}, {"n": "Santa Cruz, G\u00fcer Aike", "id": "78_021", "v": 0.09111111111111111, "c": "yellow", "max": 212}, {"n": "Santa Cruz, Lago Argentino", "id": "78_028", "v": 0.07189542483660132, "c": "yellow", "max": 37}, {"n": "Santa Cruz, Lago Buenos Aires", "id": "78_035", "v": 0.3649851632047478, "c": "yellow", "max": 131}, {"n": "Santa Cruz, Magallanes", "id": "78_042", "v": 0.030640668523676882, "c": "green", "max": 9}, {"n": "Santa Cruz, R\u00edo Chico", "id": "78_049", "v": 0.0759493670886076, "c": "green", "max": 14}, {"n": "Santa Fe, SIN ESPECIFICAR", "id": "82_0", "v": 0.0, "c": "green", "max": 0}, {"n": "Santa Fe, Belgrano", "id": "82_007", "v": 0.04950495049504951, "c": "yellow", "max": 41}, {"n": "Santa Fe, Caseros", "id": "82_014", "v": 0.295970695970696, "c": "yellow", "max": 340}, {"n": "Santa Fe, Castellanos", "id": "82_021", "v": 0.0681984844781227, "c": "yellow", "max": 291}, {"n": "Santa Fe, Constituci\u00f3n", "id": "82_028", "v": 0.15390946502057612, "c": "yellow", "max": 196}, {"n": "Santa Fe, Garay", "id": "82_035", "v": 0.10173697270471464, "c": "yellow", "max": 49}, {"n": "Santa Fe, General L\u00f3pez", "id": "82_042", "v": 0.3314427507975895, "c": "yellow", "max": 891}, {"n": "Santa Fe, General Obligado", "id": "82_049", "v": 0.22076923076923077, "c": "yellow", "max": 578}, {"n": "Santa Fe, Iriondo", "id": "82_056", "v": 0.10779436152570482, "c": "yellow", "max": 121}, {"n": "Santa Fe, La Capital", "id": "82_063", "v": 0.12233644859813085, "c": "yellow", "max": 1161}, {"n": "Santa Fe, Las Colonias", "id": "82_070", "v": 0.10896309314586995, "c": "yellow", "max": 317}, {"n": "Santa Fe, 9 de Julio", "id": "82_077", "v": 0.2820097244732577, "c": "yellow", "max": 152}, {"n": "Santa Fe, Rosario", "id": "82_084", "v": 0.14931441326530612, "c": "yellow", "max": 3543}, {"n": "Santa Fe, San Crist\u00f3bal", "id": "82_091", "v": 0.13313253012048193, "c": "yellow", "max": 218}, {"n": "Santa Fe, San Javier", "id": "82_098", "v": 0.16052631578947368, "c": "yellow", "max": 66}, {"n": "Santa Fe, San Jer\u00f3nimo", "id": "82_105", "v": 0.08872901678657075, "c": "yellow", "max": 153}, {"n": "Santa Fe, San Justo", "id": "82_112", "v": 0.14819427148194272, "c": "yellow", "max": 118}, {"n": "Santa Fe, San Lorenzo", "id": "82_119", "v": 0.12792511700468018, "c": "yellow", "max": 373}, {"n": "Santa Fe, San Mart\u00edn", "id": "82_126", "v": 0.10886806056236482, "c": "yellow", "max": 134}, {"n": "Santa Fe, Vera", "id": "82_133", "v": 0.2517857142857143, "c": "yellow", "max": 123}, {"n": "Santiago del Estero, SIN ESPECIFICAR", "id": "86_0", "v": 0.07142857142857144, "c": "green", "max": 2}, {"n": "Santiago del Estero, Aguirre", "id": "86_007", "v": 0.7049180327868853, "c": "orange", "max": 63}, {"n": "Santiago del Estero, Alberdi", "id": "86_014", "v": 0.09638554216867469, "c": "green", "max": 19}, {"n": "Santiago del Estero, Atamisqui", "id": "86_021", "v": 0.2631578947368421, "c": "yellow", "max": 40}, {"n": "Santiago del Estero, Avellaneda", "id": "86_028", "v": 0.19473684210526318, "c": "yellow", "max": 42}, {"n": "Santiago del Estero, Banda", "id": "86_035", "v": 0.20008035355564482, "c": "yellow", "max": 468}, {"n": "Santiago del Estero, Belgrano", "id": "86_042", "v": 0.11188811188811189, "c": "green", "max": 13}, {"n": "Santiago del Estero, Capital", "id": "86_049", "v": 0.2195258019525802, "c": "yellow", "max": 1447}, {"n": "Santiago del Estero, Copo", "id": "86_056", "v": 0.11728395061728394, "c": "yellow", "max": 60}, {"n": "Santiago del Estero, Choya", "id": "86_063", "v": 0.08896210873146623, "c": "yellow", "max": 72}, {"n": "Santiago del Estero, Figueroa", "id": "86_070", "v": 0.15151515151515152, "c": "yellow", "max": 30}, {"n": "Santiago del Estero, General Taboada", "id": "86_077", "v": 0.11743772241992881, "c": "yellow", "max": 39}, {"n": "Santiago del Estero, Guasay\u00e1n", "id": "86_084", "v": 0.058823529411764705, "c": "green", "max": 11}, {"n": "Santiago del Estero, Jim\u00e9nez", "id": "86_091", "v": 0.14285714285714285, "c": "yellow", "max": 21}, {"n": "Santiago del Estero, Juan F. Ibarra", "id": "86_098", "v": 0.05865921787709498, "c": "green", "max": 31}, {"n": "Santiago del Estero, Loreto", "id": "86_105", "v": 0.07894736842105263, "c": "yellow", "max": 28}, {"n": "Santiago del Estero, Mitre", "id": "86_112", "v": 0.125, "c": "green", "max": 1}, {"n": "Santiago del Estero, Moreno", "id": "86_119", "v": 0.06214689265536724, "c": "yellow", "max": 35}, {"n": "Santiago del Estero, Ojo de Agua", "id": "86_126", "v": 0.14814814814814814, "c": "yellow", "max": 23}, {"n": "Santiago del Estero, Pellegrini", "id": "86_133", "v": 0.1407035175879397, "c": "yellow", "max": 50}, {"n": "Santiago del Estero, Quebrachos", "id": "86_140", "v": 0.4, "c": "orange", "max": 45}, {"n": "Santiago del Estero, R\u00edo Hondo", "id": "86_147", "v": 0.20056100981767183, "c": "yellow", "max": 137}, {"n": "Santiago del Estero, Rivadavia", "id": "86_154", "v": 0.17431192660550457, "c": "green", "max": 19}, {"n": "Santiago del Estero, Robles", "id": "86_161", "v": 0.15091210613598674, "c": "yellow", "max": 95}, {"n": "Santiago del Estero, Salavina", "id": "86_168", "v": 0.10218978102189781, "c": "green", "max": 13}, {"n": "Santiago del Estero, San Mart\u00edn", "id": "86_175", "v": 0.16176470588235295, "c": "yellow", "max": 39}, {"n": "Santiago del Estero, Sarmiento", "id": "86_182", "v": 0.06622516556291391, "c": "green", "max": 8}, {"n": "Santiago del Estero, Sil\u00edpica", "id": "86_189", "v": 0.05319148936170213, "c": "green", "max": 6}, {"n": "Tucum\u00e1n, SIN ESPECIFICAR", "id": "90_0", "v": 0.15053763440860213, "c": "green", "max": 15}, {"n": "Tucum\u00e1n, Burruyac\u00fa", "id": "90_007", "v": 0.1332547169811321, "c": "yellow", "max": 153}, {"n": "Tucum\u00e1n, Cruz Alta", "id": "90_014", "v": 0.1690106692531523, "c": "yellow", "max": 718}, {"n": "Tucum\u00e1n, Chicligasta", "id": "90_021", "v": 0.2282608695652174, "c": "yellow", "max": 279}, {"n": "Tucum\u00e1n, Famaill\u00e1", "id": "90_028", "v": 0.1223175965665236, "c": "yellow", "max": 59}, {"n": "Tucum\u00e1n, Graneros", "id": "90_035", "v": 0.15384615384615385, "c": "yellow", "max": 46}, {"n": "Tucum\u00e1n, Juan Bautista Alberdi", "id": "90_042", "v": 0.474609375, "c": "orange", "max": 202}, {"n": "Tucum\u00e1n, La Cocha", "id": "90_049", "v": 0.1341991341991342, "c": "yellow", "max": 22}, {"n": "Tucum\u00e1n, Leales", "id": "90_056", "v": 0.140282131661442, "c": "yellow", "max": 214}, {"n": "Tucum\u00e1n, Lules", "id": "90_063", "v": 0.20254314259763853, "c": "yellow", "max": 328}, {"n": "Tucum\u00e1n, Monteros", "id": "90_070", "v": 0.13846153846153847, "c": "yellow", "max": 147}, {"n": "Tucum\u00e1n, R\u00edo Chico", "id": "90_077", "v": 0.3569641367806505, "c": "yellow", "max": 361}, {"n": "Tucum\u00e1n, Capital", "id": "90_084", "v": 0.1850426382914497, "c": "yellow", "max": 2298}, {"n": "Tucum\u00e1n, Simoca", "id": "90_091", "v": 0.14691151919866446, "c": "yellow", "max": 75}, {"n": "Tucum\u00e1n, Taf\u00ed del Valle", "id": "90_098", "v": 0.20052083333333334, "c": "yellow", "max": 64}, {"n": "Tucum\u00e1n, Taf\u00ed Viejo", "id": "90_105", "v": 0.20898292501855978, "c": "yellow", "max": 530}, {"n": "Tucum\u00e1n, Trancas", "id": "90_112", "v": 0.1519756838905775, "c": "yellow", "max": 47}, {"n": "Tucum\u00e1n, Yerba Buena", "id": "90_119", "v": 0.18869013271783036, "c": "yellow", "max": 329}, {"n": "Tierra del Fuego, SIN ESPECIFICAR", "id": "94_0", "v": 0.13999999999999999, "c": "green", "max": 7}, {"n": "Tierra del Fuego, R\u00edo Grande", "id": "94_007", "v": 0.14217252396166133, "c": "yellow", "max": 374}, {"n": "Tierra del Fuego, Ushuaia", "id": "94_014", "v": 0.08588298443370906, "c": "yellow", "max": 140}, {"n": "Tierra del Fuego, Ant\u00e1rtida Argentina", "id": "94_028", "v": 0.0, "c": "green", "max": 0}, {"n": "SIN ESPECIFICAR, SIN ESPECIFICAR", "id": "99_0", "v": 0.16919739696312364, "c": "yellow", "max": 158}, {"n": "SIN ESPECIFICAR, COMUNA 12", "id": "99_012", "v": 0.0, "c": "green", "max": 0}, {"n": "SIN ESPECIFICAR, Berisso", "id": "99_098", "v": 0.0, "c": "green", "max": 0}]