[{"n": "Antwerpen, Flanders", "id": "Antwerpen, Flanders", "v": 0.16969736755727696, "c": "yellow", "max": 3763, "date": "10/17/21"}, {"n": "BrabantWallon, Wallonia", "id": "BrabantWallon, Wallonia", "v": 0.16744120546401917, "c": "yellow", "max": 1656}, {"n": "Brussels, Brussels", "id": "Brussels, Brussels", "v": 0.13891711424009293, "c": "yellow", "max": 4320}, {"n": "Hainaut, Wallonia", "id": "Hainaut, Wallonia", "v": 0.0578011653193008, "c": "yellow", "max": 2515}, {"n": "Limburg, Flanders", "id": "Limburg, Flanders", "v": 0.1936386241193535, "c": "yellow", "max": 1305}, {"n": "Li\u00e8ge, Wallonia", "id": "Li\u00e8ge, Wallonia", "v": 0.08431681091004457, "c": "yellow", "max": 4133}, {"n": "Luxembourg, Wallonia", "id": "Luxembourg, Wallonia", "v": 0.1345955958016053, "c": "yellow", "max": 954}, {"n": "Namur, Wallonia", "id": "Namur, Wallonia", "v": 0.0841943936322737, "c": "yellow", "max": 1208}, {"n": "OostVlaanderen, Flanders", "id": "OostVlaanderen, Flanders", "v": 0.10505695660762494, "c": "yellow", "max": 2291}, {"n": "VlaamsBrabant, Flanders", "id": "VlaamsBrabant, Flanders", "v": 0.14906832298136646, "c": "yellow", "max": 2815}, {"n": "WestVlaanderen, Flanders", "id": "WestVlaanderen, Flanders", "v": 0.1230459935174168, "c": "yellow", "max": 2028}]