[{"n": "Abruzzo", "id": "Abruzzo", "v": 0.15075151424512076, "c": "yellow", "max": 1268, "date": "08/27/21"}, {"n": "Basilicata", "id": "Basilicata", "v": 0.2260569456427955, "c": "yellow", "max": 672}, {"n": "Bolzano", "id": "Bolzano", "v": 0.04481863114685432, "c": "yellow", "max": 649}, {"n": "Calabria", "id": "Calabria", "v": 0.5287744045793723, "c": "orange", "max": 3272}, {"n": "Campania", "id": "Campania", "v": 0.13297399131299387, "c": "yellow", "max": 6352}, {"n": "Emilia-Romagna", "id": "Emilia-Romagna", "v": 0.1831561874525502, "c": "yellow", "max": 7006}, {"n": "Friuli Venezia Giulia", "id": "Friuli Venezia Giulia", "v": 0.11833619312466719, "c": "yellow", "max": 1218}, {"n": "Lazio", "id": "Lazio", "v": 0.18206587214798065, "c": "yellow", "max": 6700}, {"n": "Liguria", "id": "Liguria", "v": 0.14975845410628022, "c": "yellow", "max": 2026}, {"n": "Lombardia", "id": "Lombardia", "v": 0.05766694776638915, "c": "yellow", "max": 6275}, {"n": "Marche", "id": "Marche", "v": 0.2123343591031841, "c": "yellow", "max": 2123}, {"n": "Molise", "id": "Molise", "v": 0.1098579782790309, "c": "yellow", "max": 168}, {"n": "Piemonte", "id": "Piemonte", "v": 0.05585842798951501, "c": "yellow", "max": 2926}, {"n": "Puglia", "id": "Puglia", "v": 0.1395386309316003, "c": "yellow", "max": 3229}, {"n": "Sardegna", "id": "Sardegna", "v": 0.7275954814416352, "c": "orange", "max": 4344}, {"n": "Sicilia", "id": "Sicilia", "v": 0.733799624018578, "c": "orange", "max": 16826}, {"n": "Toscana", "id": "Toscana", "v": 0.2545233232241959, "c": "yellow", "max": 8154}, {"n": "Trento", "id": "Trento", "v": 0.12316812119216203, "c": "yellow", "max": 509}, {"n": "Umbria", "id": "Umbria", "v": 0.16670750633014783, "c": "yellow", "max": 1365}, {"n": "Valle d'Aosta", "id": "Valle d'Aosta", "v": 0.04494773519163763, "c": "yellow", "max": 112}, {"n": "Veneto", "id": "Veneto", "v": 0.14332346466256737, "c": "yellow", "max": 7232}]