[{"n": "Abruzzo", "id": "Abruzzo", "v": 0.06251402078815524, "c": "yellow", "max": 497, "date": "07/24/21"}, {"n": "Basilicata", "id": "Basilicata", "v": 0.059534081104400345, "c": "yellow", "max": 151}, {"n": "Bolzano", "id": "Bolzano", "v": 0.01654519561028734, "c": "yellow", "max": 233}, {"n": "Calabria", "id": "Calabria", "v": 0.1134621281815394, "c": "yellow", "max": 695}, {"n": "Campania", "id": "Campania", "v": 0.060259563556439376, "c": "yellow", "max": 2771}, {"n": "Emilia-Romagna", "id": "Emilia-Romagna", "v": 0.08770446545655325, "c": "yellow", "max": 2885}, {"n": "Friuli Venezia Giulia", "id": "Friuli Venezia Giulia", "v": 0.03798591799301817, "c": "yellow", "max": 377}, {"n": "Lazio", "id": "Lazio", "v": 0.19453969195410817, "c": "yellow", "max": 5854}, {"n": "Liguria", "id": "Liguria", "v": 0.0676328502415459, "c": "yellow", "max": 787}, {"n": "Lombardia", "id": "Lombardia", "v": 0.04731530899273857, "c": "yellow", "max": 4976}, {"n": "Marche", "id": "Marche", "v": 0.07435784713935817, "c": "yellow", "max": 691}, {"n": "Molise", "id": "Molise", "v": 0.0835421888053467, "c": "yellow", "max": 116}, {"n": "Piemonte", "id": "Piemonte", "v": 0.023037448159588476, "c": "yellow", "max": 1095}, {"n": "Puglia", "id": "Puglia", "v": 0.04361253591857561, "c": "yellow", "max": 984}, {"n": "Sardegna", "id": "Sardegna", "v": 0.37945131791285636, "c": "yellow", "max": 2020}, {"n": "Sicilia", "id": "Sicilia", "v": 0.22912750193519849, "c": "yellow", "max": 4795}, {"n": "Toscana", "id": "Toscana", "v": 0.10286563099585319, "c": "yellow", "max": 2756}, {"n": "Trento", "id": "Trento", "v": 0.09682199901202042, "c": "yellow", "max": 324}, {"n": "Umbria", "id": "Umbria", "v": 0.08715184186882301, "c": "yellow", "max": 566}, {"n": "Valle d'Aosta", "id": "Valle d'Aosta", "v": 0.020209059233449476, "c": "yellow", "max": 32}, {"n": "Veneto", "id": "Veneto", "v": 0.11284445456615805, "c": "yellow", "max": 5045}]