[{"n": "Abruzzo", "id": "Abruzzo", "v": 0.042922306139235776, "c": "yellow", "max": 418, "date": "07/19/21"}, {"n": "Basilicata", "id": "Basilicata", "v": 0.025668679896462467, "c": "yellow", "max": 98}, {"n": "Bolzano", "id": "Bolzano", "v": 0.010974281645304515, "c": "yellow", "max": 160}, {"n": "Calabria", "id": "Calabria", "v": 0.08872533987529388, "c": "yellow", "max": 582}, {"n": "Campania", "id": "Campania", "v": 0.04547595373907583, "c": "yellow", "max": 2439}, {"n": "Emilia-Romagna", "id": "Emilia-Romagna", "v": 0.051970460349230446, "c": "yellow", "max": 1806}, {"n": "Friuli Venezia Giulia", "id": "Friuli Venezia Giulia", "v": 0.02189219572806343, "c": "yellow", "max": 252}, {"n": "Lazio", "id": "Lazio", "v": 0.11117083387392729, "c": "yellow", "max": 3438}, {"n": "Liguria", "id": "Liguria", "v": 0.03472521165159994, "c": "yellow", "max": 429}, {"n": "Lombardia", "id": "Lombardia", "v": 0.03286602862689389, "c": "yellow", "max": 3551}, {"n": "Marche", "id": "Marche", "v": 0.04729008352697356, "c": "yellow", "max": 507}, {"n": "Molise", "id": "Molise", "v": 0.06766917293233082, "c": "yellow", "max": 99}, {"n": "Piemonte", "id": "Piemonte", "v": 0.013795394971633911, "c": "yellow", "max": 690}, {"n": "Puglia", "id": "Puglia", "v": 0.026881864811880655, "c": "yellow", "max": 672}, {"n": "Sardegna", "id": "Sardegna", "v": 0.24002151694459387, "c": "yellow", "max": 1241}, {"n": "Sicilia", "id": "Sicilia", "v": 0.1539865089019131, "c": "yellow", "max": 3410}, {"n": "Toscana", "id": "Toscana", "v": 0.05518763796909492, "c": "yellow", "max": 1583}, {"n": "Trento", "id": "Trento", "v": 0.05121027498765026, "c": "yellow", "max": 170}, {"n": "Umbria", "id": "Umbria", "v": 0.03781752838356612, "c": "yellow", "max": 271}, {"n": "Valle d'Aosta", "id": "Valle d'Aosta", "v": 0.008362369337979094, "c": "green", "max": 16}, {"n": "Veneto", "id": "Veneto", "v": 0.06524709633340925, "c": "yellow", "max": 2992}]