[{"n": "Ayrshire and Arran", "id": "Ayrshire and Arran", "v": 0.5491071428571428, "c": "orange", "max": 1441, "date": "08/15/21"}, {"n": "Borders", "id": "Borders", "v": 0.35870967741935483, "c": "yellow", "max": 338}, {"n": "Dumfries and Galloway", "id": "Dumfries and Galloway", "v": 0.35646206633625616, "c": "yellow", "max": 594}, {"n": "East of England", "id": "East of England", "v": 0.3486067530238421, "c": "yellow", "max": 33183}, {"n": "Eileanan Siar (Western Isles)", "id": "Eileanan Siar (Western Isles)", "v": 0.47770700636942676, "c": "orange", "max": 56}, {"n": "England", "id": "England", "v": 0.4399135835808804, "c": "orange", "max": 46134}, {"n": "Fife", "id": "Fife", "v": 0.40376143680108434, "c": "orange", "max": 1514}, {"n": "Forth Valley", "id": "Forth Valley", "v": 0.4046043165467626, "c": "orange", "max": 942}, {"n": "Grampian", "id": "Grampian", "v": 0.387287135390322, "c": "yellow", "max": 1502}, {"n": "Greater Glasgow and Clyde", "id": "Greater Glasgow and Clyde", "v": 0.34190734055354993, "c": "yellow", "max": 4436}, {"n": "Highland", "id": "Highland", "v": 0.5485915492957747, "c": "orange", "max": 955}, {"n": "Lanarkshire", "id": "Lanarkshire", "v": 0.5913213178739525, "c": "orange", "max": 3326}, {"n": "London", "id": "London", "v": 0.2775808140851449, "c": "yellow", "max": 49982}, {"n": "Lothian", "id": "Lothian", "v": 0.30486075662185924, "c": "yellow", "max": 3444}, {"n": "Midlands", "id": "Midlands", "v": 0.4582044945855381, "c": "orange", "max": 67085}, {"n": "NOT SPECIFIED", "id": "NOT SPECIFIED", "v": 0.0, "c": "green", "max": 0}, {"n": "North East and Yorkshire", "id": "North East and Yorkshire", "v": 0.3399204443980563, "c": "yellow", "max": 56847}, {"n": "North West", "id": "North West", "v": 0.36063273174038296, "c": "yellow", "max": 43376}, {"n": "Northern Ireland", "id": "Northern Ireland", "v": 0.729841488628532, "c": "orange", "max": 20170}, {"n": "Orkney", "id": "Orkney", "v": 0.5, "c": "orange", "max": 20}, {"n": "Scotland", "id": "Scotland", "v": -0.049999999999999996, "c": "green", "max": 4}, {"n": "Shetland", "id": "Shetland", "v": 0.281437125748503, "c": "yellow", "max": 32}, {"n": "South East", "id": "South East", "v": 0.381557869443332, "c": "yellow", "max": 48121}, {"n": "South West", "id": "South West", "v": 0.5286303132137887, "c": "orange", "max": 38135}, {"n": "Tayside", "id": "Tayside", "v": 0.1801165657924232, "c": "yellow", "max": 1076}, {"n": "Wales", "id": "Wales", "v": 0.3120750590360873, "c": "yellow", "max": 11753}]