[{"n": "Carlow", "id": "Carlow", "v": 0.13270405330372015, "c": "yellow", "max": 326, "date": "10/01/21"}, {"n": "Cavan", "id": "Cavan", "v": 0.09260892573646146, "c": "yellow", "max": 381}, {"n": "Clare", "id": "Clare", "v": 0.08103061986557132, "c": "yellow", "max": 322}, {"n": "Cork", "id": "Cork", "v": 0.08050603795284646, "c": "yellow", "max": 1559}, {"n": "Donegal", "id": "Donegal", "v": 0.08183560987299304, "c": "yellow", "max": 1115}, {"n": "Dublin", "id": "Dublin", "v": 0.08260000391980087, "c": "yellow", "max": 6047}, {"n": "Galway", "id": "Galway", "v": 0.07461132704053304, "c": "yellow", "max": 771}, {"n": "Kerry", "id": "Kerry", "v": 0.11655773420479304, "c": "yellow", "max": 515}, {"n": "Kildare", "id": "Kildare", "v": 0.10011551790527531, "c": "yellow", "max": 943}, {"n": "Kilkenny", "id": "Kilkenny", "v": 0.07816968541468064, "c": "yellow", "max": 242}, {"n": "Laois", "id": "Laois", "v": 0.08018969605518432, "c": "yellow", "max": 314}, {"n": "Leitrim", "id": "Leitrim", "v": 0.1535608308605341, "c": "yellow", "max": 132}, {"n": "Limerick", "id": "Limerick", "v": 0.07588666534574996, "c": "yellow", "max": 802}, {"n": "Longford", "id": "Longford", "v": 0.1474756421612046, "c": "yellow", "max": 236}, {"n": "Louth", "id": "Louth", "v": 0.0633430083660577, "c": "yellow", "max": 689}, {"n": "Mayo", "id": "Mayo", "v": 0.0822601229841049, "c": "yellow", "max": 570}, {"n": "Meath", "id": "Meath", "v": 0.0892436974789916, "c": "yellow", "max": 805}, {"n": "Monaghan", "id": "Monaghan", "v": 0.06375092661230541, "c": "yellow", "max": 329}, {"n": "Offaly", "id": "Offaly", "v": 0.06293567018522207, "c": "yellow", "max": 232}, {"n": "Roscommon", "id": "Roscommon", "v": 0.08284189834316202, "c": "yellow", "max": 195}, {"n": "Sligo", "id": "Sligo", "v": 0.09654036243822076, "c": "yellow", "max": 196}, {"n": "Tipperary", "id": "Tipperary", "v": 0.08977287998924875, "c": "yellow", "max": 491}, {"n": "Waterford", "id": "Waterford", "v": 0.12433392539964476, "c": "yellow", "max": 495}, {"n": "Westmeath", "id": "Westmeath", "v": 0.08029978586723768, "c": "yellow", "max": 338}, {"n": "Wexford", "id": "Wexford", "v": 0.0524743007410949, "c": "yellow", "max": 313}, {"n": "Wicklow", "id": "Wicklow", "v": 0.07150223444482641, "c": "yellow", "max": 288}]