[{"n": "Blekinge", "id": "Blekinge", "v": 1.0, "c": "red", "max": 2508, "t": 18687, "date": "01/19/22"}, {"n": "Dalarna", "id": "Dalarna", "v": 0.8869368314203171, "c": "red", "max": 7845, "t": 42563}, {"n": "Gotland", "id": "Gotland", "v": 0.9127049180327869, "c": "red", "max": 1404, "t": 6925}, {"n": "G\u00e4vleborg", "id": "G\u00e4vleborg", "v": 0.9574254717841189, "c": "red", "max": 6216, "t": 49530}, {"n": "Halland", "id": "Halland", "v": 1.0, "c": "red", "max": 14975, "t": 67537}, {"n": "J\u00e4mtland_H\u00e4rjedalen", "id": "J\u00e4mtland_H\u00e4rjedalen", "v": 0.8913103195678052, "c": "red", "max": 6434, "t": 22995}, {"n": "J\u00f6nk\u00f6ping", "id": "J\u00f6nk\u00f6ping", "v": 1.0, "c": "red", "max": 9190, "t": 60738}, {"n": "Kalmar", "id": "Kalmar", "v": 1.0, "c": "red", "max": 5156, "t": 35719}, {"n": "Kronoberg", "id": "Kronoberg", "v": 0.8945703742751713, "c": "red", "max": 5572, "t": 31966}, {"n": "Norrbotten", "id": "Norrbotten", "v": 1.0, "c": "red", "max": 4182, "t": 35250}, {"n": "Sk\u00e5ne", "id": "Sk\u00e5ne", "v": 0.9425796059161393, "c": "red", "max": 38607, "t": 243203}, {"n": "Stockholm", "id": "Stockholm", "v": 1.0, "c": "red", "max": 83011, "t": 428016}, {"n": "S\u00f6rmland", "id": "S\u00f6rmland", "v": 1.0, "c": "red", "max": 9061, "t": 41668}, {"n": "Uppsala", "id": "Uppsala", "v": 1.0, "c": "red", "max": 10829, "t": 61523}, {"n": "V\u00e4rmland", "id": "V\u00e4rmland", "v": 0.9897578404128622, "c": "red", "max": 8165, "t": 35433}, {"n": "V\u00e4sterbotten", "id": "V\u00e4sterbotten", "v": 0.8989954138458178, "c": "red", "max": 5617, "t": 35360}, {"n": "V\u00e4sternorrland", "id": "V\u00e4sternorrland", "v": 1.0, "c": "red", "max": 5047, "t": 36486}, {"n": "V\u00e4stmanland", "id": "V\u00e4stmanland", "v": 1.0, "c": "red", "max": 8387, "t": 47902}, {"n": "V\u00e4stra_G\u00f6taland", "id": "V\u00e4stra_G\u00f6taland", "v": 0.9793533254237751, "c": "red", "max": 48931, "t": 287344}, {"n": "\u00d6rebro", "id": "\u00d6rebro", "v": 0.989485267147573, "c": "red", "max": 9705, "t": 51913}, {"n": "\u00d6sterg\u00f6tland", "id": "\u00d6sterg\u00f6tland", "v": 1.0, "c": "red", "max": 9736, "t": 59578}]