[{"n": "Albacete", "id": "AB", "v": 0.009273957724120645, "c": "yellow", "max": 437, "date": "04/05/22"}, {"n": "Alicante/Alacant", "id": "A", "v": 0.011758907196169554, "c": "yellow", "max": 3085}, {"n": "Almer\u00eda", "id": "AL", "v": 0.030364778193479425, "c": "yellow", "max": 1405}, {"n": "Araba/\u00c1lava", "id": "VI", "v": 0.020720029361716328, "c": "yellow", "max": 844}, {"n": "Asturias", "id": "O", "v": 0.06221224772686018, "c": "yellow", "max": 3861}, {"n": "Badajoz", "id": "BA", "v": 0.04869547388384848, "c": "yellow", "max": 2812}, {"n": "Balears, Illes", "id": "PM", "v": 0.03192303487482234, "c": "yellow", "max": 3082}, {"n": "Barcelona", "id": "B", "v": 0.014265086301950398, "c": "yellow", "max": 10745}, {"n": "Bizkaia", "id": "BI", "v": 0.017304616882213877, "c": "yellow", "max": 2640}, {"n": "Burgos", "id": "BU", "v": 0.02460506519558676, "c": "yellow", "max": 810}, {"n": "Cantabria", "id": "S", "v": 0.030014889893158488, "c": "yellow", "max": 1354}, {"n": "Castell\u00f3n/Castell\u00f3", "id": "CS", "v": 0.013354450883697492, "c": "yellow", "max": 1239}, {"n": "Ceuta", "id": "CE", "v": 0.025730014360938247, "c": "yellow", "max": 275}, {"n": "Ciudad Real", "id": "CR", "v": 0.015768056968463885, "c": "yellow", "max": 914}, {"n": "Coru\u00f1a, A", "id": "C", "v": 0.07934141546526868, "c": "yellow", "max": 6245}, {"n": "Cuenca", "id": "CU", "v": 0.00992133796329105, "c": "yellow", "max": 258}, {"n": "C\u00e1ceres", "id": "CC", "v": 0.037420481476861674, "c": "yellow", "max": 1281}, {"n": "C\u00e1diz", "id": "CA", "v": 0.042222682486611235, "c": "yellow", "max": 2420}, {"n": "C\u00f3rdoba", "id": "CO", "v": 0.032168712621970415, "c": "yellow", "max": 1436}, {"n": "Gipuzkoa", "id": "SS", "v": 0.013868549184534314, "c": "yellow", "max": 1549}, {"n": "Girona", "id": "GI", "v": 0.017112461170519833, "c": "yellow", "max": 1615}, {"n": "Granada", "id": "GR", "v": 0.022829329565080863, "c": "yellow", "max": 1111}, {"n": "Guadalajara", "id": "GU", "v": 0.005571175674268457, "c": "yellow", "max": 231}, {"n": "Huelva", "id": "H", "v": 0.04052543320290665, "c": "yellow", "max": 983}, {"n": "Huesca", "id": "HU", "v": 0.0209767467071386, "c": "yellow", "max": 491}, {"n": "Ja\u00e9n", "id": "J", "v": 0.023469044414535668, "c": "yellow", "max": 876}, {"n": "Le\u00f3n", "id": "LE", "v": 0.04772047960971588, "c": "yellow", "max": 1505}, {"n": "Lleida", "id": "L", "v": 0.01731971184015663, "c": "yellow", "max": 913}, {"n": "Lugo", "id": "LU", "v": 0.08161970043158162, "c": "yellow", "max": 1655}, {"n": "Madrid", "id": "M", "v": 0.01827830838207916, "c": "yellow", "max": 9535}, {"n": "Melilla", "id": "ML", "v": 0.019062609303952434, "c": "yellow", "max": 135}, {"n": "Murcia", "id": "MU", "v": 0.02454245109864178, "c": "yellow", "max": 4329}, {"n": "M\u00e1laga", "id": "MA", "v": 0.0477483164983165, "c": "yellow", "max": 3774}, {"n": "Navarra", "id": "NA", "v": 0.02738323225875093, "c": "yellow", "max": 2399}, {"n": "Ourense", "id": "OR", "v": 0.049496737086605465, "c": "yellow", "max": 1369}, {"n": "Palencia", "id": "P", "v": 0.03623834616943657, "c": "yellow", "max": 475}, {"n": "Palmas, Las", "id": "CN", "v": 0.0980478335714024, "c": "yellow", "max": 6204}, {"n": "Pontevedra", "id": "PO", "v": 0.06591397276810282, "c": "yellow", "max": 4600}, {"n": "Rioja, La", "id": "LO", "v": 0.03545003950865599, "c": "yellow", "max": 1065}, {"n": "Salamanca", "id": "SA", "v": 0.02896995708154506, "c": "yellow", "max": 764}, {"n": "Santa Cruz de Tenerife", "id": "TF", "v": 0.07886371866575463, "c": "yellow", "max": 4810}, {"n": "Segovia", "id": "SG", "v": 0.01589293182768716, "c": "yellow", "max": 229}, {"n": "Sevilla", "id": "SE", "v": 0.02635215538750912, "c": "yellow", "max": 2422}, {"n": "Soria", "id": "SO", "v": 0.043286867204695524, "c": "yellow", "max": 283}, {"n": "Tarragona", "id": "T", "v": 0.020691143543122285, "c": "yellow", "max": 1969}, {"n": "Teruel", "id": "TE", "v": 0.01855256560254053, "c": "yellow", "max": 318}, {"n": "Toledo", "id": "TO", "v": 0.009500459699662888, "c": "yellow", "max": 737}, {"n": "Valencia/Val\u00e8ncia", "id": "V", "v": 0.029168601506063024, "c": "yellow", "max": 11958}, {"n": "Valladolid", "id": "VA", "v": 0.033374011779062976, "c": "yellow", "max": 1415}, {"n": "Zamora", "id": "ZA", "v": 0.051843108770655524, "c": "yellow", "max": 554}, {"n": "Zaragoza", "id": "Z", "v": 0.012321741305979485, "c": "yellow", "max": 1697}, {"n": "\u00c1vila", "id": "AV", "v": 0.02204195345788266, "c": "yellow", "max": 312}]